beetsplug/__init__.py
beetsplug/beetfs.py
beets_beetfs-0.8.0.dist-info/LICENSE
beets_beetfs-0.8.0.dist-info/WHEEL
beets_beetfs-0.8.0.dist-info/METADATA
beets_beetfs-0.8.0.dist-info/RECORD
