Metadata-Version: 2.1
Name: beets-beetfs
Version: 0.8.0
Summary: A beets plugin for mounting a FUSE filesystem of audio items
License: MIT
Author: Drew Abbott
Author-email: abbotta4@gmail.com
Requires-Python: >=3.6,<4.0
Classifier: License :: OSI Approved :: MIT License
Classifier: Programming Language :: Python :: 3
Classifier: Programming Language :: Python :: 3.10
Classifier: Programming Language :: Python :: 3.6
Classifier: Programming Language :: Python :: 3.7
Classifier: Programming Language :: Python :: 3.8
Classifier: Programming Language :: Python :: 3.9
Requires-Dist: beets (>=1.6.0,<2.0.0)
Requires-Dist: mutagen (>=1.45.1,<2.0.0)
Requires-Dist: pyfuse3 (>=3.2.1,<4.0.0)
Requires-Dist: trio (>=0.19.0,<0.20.0)
